bassmap/Foliumatic.py
bassmap/__init__.py
bassmap/bassmap.py
bassmap-0.1.1.dist-info/LICENSE
bassmap-0.1.1.dist-info/METADATA
bassmap-0.1.1.dist-info/WHEEL
bassmap-0.1.1.dist-info/dependency_links.txt
bassmap-0.1.1.dist-info/top_level.txt
bassmap-0.1.1.dist-info/RECORD
