Metadata-Version: 2.1
Name: bassmap
Version: 0.1.1
Summary: Python Boilerplate contains all the boilerplate you need to create a Python package.
Home-page: https://github.com/bassneel/bassmap
Author: Bass Neel
Author-email: maps.bassneel@gmail.com
License: MIT license
Keywords: bassmap
Classifier: Development Status :: 2 - Pre-Alpha
Classifier: Intended Audience :: Developers
Classifier: License :: OSI Approved :: MIT License
Classifier: Natural Language :: English
Classifier: Programming Language :: Python :: 3
Classifier: Programming Language :: Python :: 3.7
Classifier: Programming Language :: Python :: 3.8
Classifier: Programming Language :: Python :: 3.9
Classifier: Programming Language :: Python :: 3.10
Requires-Python: >=3.7
License-File: LICENSE
Requires-Dist: leafmap
Requires-Dist: pycrs
Requires-Dist: httpx
Requires-Dist: requests
Requires-Dist: geopandas
Requires-Dist: ipyleaflet
Requires-Dist: rasterio
Requires-Dist: numpy
Requires-Dist: matplotlib
Requires-Dist: folium
